{"fpath": [{"path": "images/72.jpg", "fname": "72.jpg"}, {"path": "images/11.jpg", "fname": "11.jpg"}, {"path": "images/63.jpg", "fname": "63.jpg"}, {"path": "images/44.jpg", "fname": "44.jpg"}, {"path": "images/47.jpg", "fname": "47.jpg"}, {"path": "images/53.jpg", "fname": "53.jpg"}, {"path": "images/5.jpg", "fname": "5.jpg"}, {"path": "images/1.jpg", "fname": "1.jpg"}, {"path": "images/71.jpg", "fname": "71.jpg"}, {"path": "images/49.jpg", "fname": "49.jpg"}, {"path": "images/16.jpg", "fname": "16.jpg"}, {"path": "images/9.jpg", "fname": "9.jpg"}, {"path": "images/46.jpg", "fname": "46.jpg"}, {"path": "images/56.jpg", "fname": "56.jpg"}, {"path": "images/7.jpg", "fname": "7.jpg"}, {"path": "images/22.jpg", "fname": "22.jpg"}, {"path": "images/55.jpg", "fname": "55.jpg"}, {"path": "images/62.jpg", "fname": "62.jpg"}, {"path": "images/12.jpg", "fname": "12.jpg"}, {"path": "images/28.jpg", "fname": "28.jpg"}, {"path": "images/15.jpg", "fname": "15.jpg"}, {"path": "images/35.jpg", "fname": "35.jpg"}, {"path": "images/10.jpg", "fname": "10.jpg"}, {"path": "images/21.jpg", "fname": "21.jpg"}, {"path": "images/40.jpg", "fname": "40.jpg"}, {"path": "images/48.jpg", "fname": "48.jpg"}, {"path": "images/26.jpg", "fname": "26.jpg"}, {"path": "images/25.jpg", "fname": "25.jpg"}, {"path": "images/60.jpg", "fname": "60.jpg"}, {"path": "images/54.jpg", "fname": "54.jpg"}, {"path": "images/2.jpg", "fname": "2.jpg"}, {"path": "images/52.jpg", "fname": "52.jpg"}, {"path": "images/17.jpg", "fname": "17.jpg"}, {"path": "images/33.jpg", "fname": "33.jpg"}, {"path": "images/58.jpg", "fname": "58.jpg"}, {"path": "images/68.jpg", "fname": "68.jpg"}, {"path": "images/69.jpg", "fname": "69.jpg"}, {"path": "images/19.jpg", "fname": "19.jpg"}, {"path": "images/59.jpg", "fname": "59.jpg"}, {"path": "images/73.jpg", "fname": "73.jpg"}, {"path": "images/66.jpg", "fname": "66.jpg"}, {"path": "images/29.jpg", "fname": "29.jpg"}, {"path": "images/57.jpg", "fname": "57.jpg"}, {"path": "images/32.jpg", "fname": "32.jpg"}, {"path": "images/39.jpg", "fname": "39.jpg"}, {"path": "images/8.jpg", "fname": "8.jpg"}, {"path": "images/34.jpg", "fname": "34.jpg"}, {"path": "images/4.jpg", "fname": "4.jpg"}, {"path": "images/43.jpg", "fname": "43.jpg"}, {"path": "images/37.jpg", "fname": "37.jpg"}, {"path": "images/24.jpg", "fname": "24.jpg"}, {"path": "images/51.jpg", "fname": "51.jpg"}, {"path": "images/20.jpg", "fname": "20.jpg"}, {"path": "images/27.jpg", "fname": "27.jpg"}, {"path": "images/13.jpg", "fname": "13.jpg"}, {"path": "images/36.jpg", "fname": "36.jpg"}, {"path": "images/41.jpg", "fname": "41.jpg"}, {"path": "images/38.jpg", "fname": "38.jpg"}, {"path": "images/45.jpg", "fname": "45.jpg"}, {"path": "images/18.jpg", "fname": "18.jpg"}, {"path": "images/64.jpg", "fname": "64.jpg"}, {"path": "images/50.jpg", "fname": "50.jpg"}, {"path": "images/14.jpg", "fname": "14.jpg"}, {"path": "images/3.jpg", "fname": "3.jpg"}, {"path": "images/42.jpg", "fname": "42.jpg"}, {"path": "images/70.jpg", "fname": "70.jpg"}, {"path": "images/61.jpg", "fname": "61.jpg"}, {"path": "images/30.jpg", "fname": "30.jpg"}, {"path": "images/67.jpg", "fname": "67.jpg"}, {"path": "images/31.jpg", "fname": "31.jpg"}, {"path": "images/6.jpg", "fname": "6.jpg"}, {"path": "images/23.jpg", "fname": "23.jpg"}, {"path": "images/65.jpg", "fname": "65.jpg"}]}